Workbook

Sheet Шаблон
A1: Объект | B1: Водитель | C1: Email водителя | D1: Плановая дата
A2: Вызревание | B2: ВодительНФ | D2: =VLOOKUP(A2,Лист1!$A$2:$E$2486,5,FALSE) -> 46266
A3: Косметолог | B3: ВодительНФ | D3: =VLOOKUP(A3,Лист1!$A$2:$E$2486,5,FALSE) -> 46266
A4: Мятый | B4: ВодительНФ | D4: =VLOOKUP(A4,Лист1!$A$2:$E$2486,5,FALSE) -> 46266
A5: Оберн | B5: ВодительНФ | D5: =VLOOKUP(A5,Лист1!$A$2:$E$2486,5,FALSE) -> 46266
A6: 50473 | B6: ВодительНФ | D6: =VLOOKUP(A6,Лист1!$A$2:$E$2486,5,FALSE) -> 46276
A7: 50856 | B7: ВодительНФ | D7: =VLOOKUP(A7,Лист1!$A$2:$E$2486,5,FALSE) -> 46276
A8: Глаголево | B8: ВодительНФ | D8: =VLOOKUP(A8,Лист1!$A$2:$E$2486,5,FALSE) -> 46266
A9: Жемчуг | B9: ВодительНФ | D9: =VLOOKUP(A9,Лист1!$A$2:$E$2486,5,FALSE) -> 46266
A10: Квеми | B10: ВодительНФ | D10: =VLOOKUP(A10,Лист1!$A$2:$E$2486,5,FALSE) -> 46266
A11: Квемо | B11: ВодительНФ | D11: =VLOOKUP(A11,Лист1!$A$2:$E$2486,5,FALSE) -> 46276
A12: Компьютерка | B12: ВодительНФ | D12: =VLOOKUP(A12,Лист1!$A$2:$E$2486,5,FALSE) -> 46266
A13: Наковка | B13: ВодительНФ | D13: =VLOOKUP(A13,Лист1!$A$2:$E$2486,5,FALSE) -> 46266
... A582: Интрузия | B582: Гончаров Артём | D582: =VLOOKUP(A582,Лист1!$A$2:$E$2486,5,FALSE) -> 46272
A583: 90463 | B583: Гончаров Артём
A584: 90653 | B584: Гончаров Артём
A585: 90664 | B585: Гончаров Артём
A586: Градусник | B586: Гончаров Артём
A587: Пелотас | B587: Гончаров Артём
A588: Андания | B588: Гришин Николай Сергеевич | D588: =VLOOKUP(A588,Лист1!$A$2:$E$2486,5,FALSE) -> 46266
A589: Гакрукс | B589: Гришин Николай Сергеевич | D589: =VLOOKUP(A589,Лист1!$A$2:$E$2486,5,FALSE) -> 46266
A590: Саночник | B590: Гришин Николай Сергеевич | D590: =VLOOKUP(A590,Лист1!$A$2:$E$2486,5,FALSE) -> 46266
A591: 77574 | B591: Гришин Николай Сергеевич | D591: =VLOOKUP(A591,Лист1!$A$2:$E$2486,5,FALSE) -> 46266
A592: Белгородская | B592: Гришин Николай Сергеевич | D592: =VLOOKUP(A592,Лист1!$A$2:$E$2486,5,FALSE) -> 46266
A593: Непобедимая | B593: Гришин Николай Сергеевич | D593: =VLOOKUP(A593,Лист1!$A$2:$E$2486,5,FALSE) -> 46266
A594: Поприще | B594: Гришин Николай Сергеевич | D594: =VLOOKUP(A594,Лист1!$A$2:$E$2486,5,FALSE) -> 46266
A595: Степурино | B595: Гришин Николай Сергеевич | D595: =VLOOKUP(A595,Лист1!$A$2:$E$2486,5,FALSE) -> 46266
A596: Терпенье | B596: Гришин Николай Сергеевич | D596: =VLOOKUP(A596,Лист1!$A$2:$E$2486,5,FALSE) -> 46266
A597: Головнин | B597: Гришин Николай Сергеевич | D597: =VLOOKUP(A597,Лист1!$A$2:$E$2486,5,FALSE) -> 46267
A598: Жакоби | B598: Гришин Николай Сергеевич | D598: =VLOOKUP(A598,Лист1!$A$2:$E$2486,5,FALSE) -> 46266
A599: Зернохранилище | B599: Гришин Николай Сергеевич | D599: =VLOOKUP(A599,Лист1!$A$2:$E$2486,5,FALSE) -> 46268
... A932: 33079 | B932: Гришин Николай Сергеевич | D932: =VLOOKUP(A932,Лист1!$A$2:$E$2486,5,FALSE) -> 46289
A933: 77975 | B933: Гришин Николай Сергеевич
A934: ММ приметив | B934: Гришин Николай Сергеевич
A935: 50804 | B935: Динаев Дмитрий Вадимович | D935: =VLOOKUP(A935,Лист1!$A$2:$E$2486,5,FALSE) -> 46266
A936: Секарево | B936: Динаев Дмитрий Вадимович | D936: =VLOOKUP(A936,Лист1!$A$2:$E$2486,5,FALSE) -> 46282
A937: Сухоблюдное | B937: Динаев Дмитрий Вадимович | D937: =VLOOKUP(A937,Лист1!$A$2:$E$2486,5,FALSE) -> 46282
A938: 77352 | B938: Динаев Дмитрий Вадимович | D938: =VLOOKUP(A938,Лист1!$A$2:$E$2486,5,FALSE) -> 46276
A939: 50642 | B939: Динаев Дмитрий Вадимович | D939: =VLOOKUP(A939,Лист1!$A$2:$E$2486,5,FALSE) -> 46276
A940: Мохлин | B940: Динаев Дмитрий Вадимович | D940: =VLOOKUP(A940,Лист1!$A$2:$E$2486,5,FALSE) -> 46282
A941: Аптека Граненый | B941: Динаев Дмитрий Вадимович | D941: =VLOOKUP(A941,Лист1!$A$2:$E$2486,5,FALSE) -> 46282
A942: Бугай | B942: Динаев Дмитрий Вадимович | D942: =VLOOKUP(A942,Лист1!$A$2:$E$2486,5,FALSE) -> 46282
A943: Граненый | B943: Динаев Дмитрий Вадимович | D943: =VLOOKUP(A943,Лист1!$A$2:$E$2486,5,FALSE) -> 46282
A944: Растворимый | B944: Динаев Дмитрий Вадимович | D944: =VLOOKUP(A944,Лист1!$A$2:$E$2486,5,FALSE) -> 46282
A945: Рентригель | B945: Динаев Дмитрий Вадимович | D945: =VLOOKUP(A945,Лист1!$A$2:$E$2486,5,FALSE) -> 46282
A946: 50723 | B946: Динаев Дмитрий Вадимович | D946: =VLOOKUP(A946,Лист1!$A$2:$E$2486,5,FALSE) -> 46282
... A1313: Лестэ | B1313: Динаев Дмитрий Вадимович | D1313: =VLOOKUP(A1313,Лист1!$A$2:$E$2486,5,FALSE) -> 46281
A1314: Скирдовальщик | B1314: Динаев Дмитрий Вадимович
A1315: Софтадес | B1315: Динаев Дмитрий Вадимович
A1316: Сандаловый | B1316: Динаев Дмитрий Вадимович
A1317: Мусинская | B1317: Ковылин Александр | D1317: =VLOOKUP(A1317,Лист1!$A$2:$E$2486,5,FALSE) -> 46266
A1318: Напарье | B1318: Ковылин Александр | D1318: =VLOOKUP(A1318,Лист1!$A$2:$E$2486,5,FALSE) -> 46266
A1319: Подрастание | B1319: Ковылин Александр | D1319: =VLOOKUP(A1319,Лист1!$A$2:$E$2486,5,FALSE) -> 46266
A1320: Теруэль | B1320: Ковылин Александр | D1320: =VLOOKUP(A1320,Лист1!$A$2:$E$2486,5,FALSE) -> 46266
A1321: 90451 | B1321: Ковылин Александр | D1321: =VLOOKUP(A1321,Лист1!$A$2:$E$2486,5,FALSE) -> 46266
A1322: 90618 | B1322: Ковылин Александр | D1322: =VLOOKUP(A1322,Лист1!$A$2:$E$2486,5,FALSE) -> 46266
A1323: 90662 | B1323: Ковылин Александр | D1323: =VLOOKUP(A1323,Лист1!$A$2:$E$2486,5,FALSE) -> 46266
A1324: 50043 | B1324: Ковылин Александр | D1324: =VLOOKUP(A1324,Лист1!$A$2:$E$2486,5,FALSE) -> 46266
A1325: Аптека Детскосельская | B1325: Ковылин Александр | D1325: =VLOOKUP(A1325,Лист1!$A$2:$E$2486,5,FALSE) -> 46266
A1326: Аптека Пикеринг | B1326: Ковылин Александр | D1326: =VLOOKUP(A1326,Лист1!$A$2:$E$2486,5,FALSE) -> 46266
A1327: Демаскировка | B1327: Ковылин Александр | D1327: =VLOOKUP(A1327,Лист1!$A$2:$E$2486,5,FALSE) -> 46266
A1328: Заовражное | B1328: Ковылин Александр | D1328: =VLOOKUP(A1328,Лист1!$A$2:$E$2486,5,FALSE) -> 46266
... A1700: Рыбальский | B1700: Ковылин Александр | D1700: =VLOOKUP(A1700,Лист1!$A$2:$E$2486,5,FALSE) -> 46279
A1701: 1062 | B1701: Ковылин Александр | D1701: =VLOOKUP(A1701,Лист1!$A$2:$E$2486,5,FALSE) -> 46279
A1702: 1205 | B1702: Ковылин Александр | D1702: =VLOOKUP(A1702,Лист1!$A$2:$E$2486,5,FALSE) -> 46279
A1703: 1298 | B1703: Ковылин Александр | D1703: =VLOOKUP(A1703,Лист1!$A$2:$E$2486,5,FALSE) -> 46279
A1704: 1358 | B1704: Ковылин Александр | D1704: =VLOOKUP(A1704,Лист1!$A$2:$E$2486,5,FALSE) -> 46279
A1705: 1992 | B1705: Ковылин Александр | D1705: =VLOOKUP(A1705,Лист1!$A$2:$E$2486,5,FALSE) -> 46279
A1706: 5341 | B1706: Ковылин Александр | D1706: =VLOOKUP(A1706,Лист1!$A$2:$E$2486,5,FALSE) -> 46279
A1707: 5371 | B1707: Ковылин Александр | D1707: =VLOOKUP(A1707,Лист1!$A$2:$E$2486,5,FALSE) -> 46279
A1708: 90661 | B1708: Ковылин Александр
A1709: 77800 | B1709: Мазим Максим Александрович | D1709: =VLOOKUP(A1709,Лист1!$A$2:$E$2486,5,FALSE) -> 46273
A1710: 50893 | B1710: Мазим Максим Александрович | D1710: =VLOOKUP(A1710,Лист1!$A$2:$E$2486,5,FALSE) -> 46293
A1711: 90604 | B1711: Мазим Максим Александрович | D1711: =VLOOKUP(A1711,Лист1!$A$2:$E$2486,5,FALSE) -> 46293
A1712: Греймут | B1712: Мазим Максим Александрович | D1712: =VLOOKUP(A1712,Лист1!$A$2:$E$2486,5,FALSE) -> 46273
A1713: Огайо | B1713: Мазим Максим Александрович | D1713: =VLOOKUP(A1713,Лист1!$A$2:$E$2486,5,FALSE) -> 46273
A1714: Редуктор | B1714: Мазим Максим Александрович | D1714: =VLOOKUP(A1714,Лист1!$A$2:$E$2486,5,FALSE) -> 46273
A1715: 77905 | B1715: Мазим Максим Александрович | D1715: =VLOOKUP(A1715,Лист1!$A$2:$E$2486,5,FALSE) -> 46273
A1716: 77055 | B1716: Мазим Максим Александрович | D1716: =VLOOKUP(A1716,Лист1!$A$2:$E$2486,5,FALSE) -> 46273
A1717: 77152 | B1717: Мазим Максим Александрович | D1717: =VLOOKUP(A1717,Лист1!$A$2:$E$2486,5,FALSE) -> 46273
A1718: 77174 | B1718: Мазим Максим Александрович | D1718: =VLOOKUP(A1718,Лист1!$A$2:$E$2486,5,FALSE) -> 46273
A1719: 77553 | B1719: Мазим Максим Александрович | D1719: =VLOOKUP(A1719,Лист1!$A$2:$E$2486,5,FALSE) -> 46273
A1720: S77-0134 | B1720: Мазим Максим Александрович | D1720: =VLOOKUP(A1720,Лист1!$A$2:$E$2486,5,FALSE) -> 46273
... A1820: Лоиза | B1820: Мазим Максим Александрович | D1820: =VLOOKUP(A1820,Лист1!$A$2:$E$2486,5,FALSE) -> 46281
A1821: Амадео | B1821: Мазим Максим Александрович
A1822: Анаксагор | B1822: Мазим Максим Александрович
A1823: Баландино | B1823: Мазим Максим Александрович
A1824: Боярский | B1824: Мазим Максим Александрович
A1825: Горкино | B1825: Мазим Максим Александрович
A1826: Дзонаро | B1826: Мазим Максим Александрович
A1827: Кичиро | B1827: Мазим Максим Александрович
A1828: Легковерный | B1828: Мазим Максим Александрович | D1828: =VLOOKUP(A1828,Лист1!$A$2:$E$2486,5,FALSE) -> 46274
A1829: Намокание | B1829: Мазим Максим Александрович
A1830: Новобаландино | B1830: Мазим Максим Александрович
A1831: Подрессорник | B1831: Мазим Максим Александрович
A1832: Суналы | B1832: Мазим Максим Александрович
A1833: Теренций | B1833: Мазим Максим Александрович
A1834: Фарнборо | B1834: Мазим Максим Александрович
A1835: Хорасан | B1835: Мазим Максим Александрович
A1836: НовоТроицк | B1836: Мазим Максим Александрович | D1836: =VLOOKUP(A1836,Лист1!$A$2:$E$2486,5,FALSE) -> 46277
...

Sheet Лист1
A1: объект
A2: 77800 | C2: Москва Север | D2: Москва, Кочновский проезд, д.4к1 | E2: 46273
A3: 50893 | B3: Бастион | C3: Звенигород, Клин, Краснознаменск | D3: 141601, Московская обл, Клинский р-н, Клин г, Ленинградская ул, д.52 | E3: 46293
A4: 90604 | B4: Бастион | C4: Звенигород, Клин, Краснознаменск | D4: МО, г.о.Клин, с.Петровское, ул.Лесхозная, д.5А | E4: 46293
A5: Лотрек | B5: Альт | C5: Щёлково | D5: МО, Щелково ул. Заповедная д.1Б | E5: 46266
A6: Мусинская | B6: Альт | C6: Щёлково | D6: 141143, МО, г. Щелково, д. Медвежьи Озера, стр.67Г | E6: 46266
A7: Напарье | B7: Альт | C7: Щёлково | D7: 141181, Московская обл, Щелковский р-н, Загорянский дп, Орджоникидзе ул, дом № Владение 46А, часть | E7: 46266
A8: Подрастание | B8: Альт | C8: Щёлково | D8: щелково 3 институтская стр.28 | E8: 46266
A9: Теруэль | B9: Альт | C9: Щёлково | D9: 141142, Московская обл, Щелковский р-н, Биокомбината п, дом № 6А | E9: 46266
A10: 90451 | B10: Бастион | C10: Щёлково | D10: МО, Щёлковский р-н, д.Большие Жеребцы, д.33в | E10: 46266
A11: 90618 | B11: Бастион | C11: Щёлково | D11: МО, г.о.Щелково, пгт.Загорянский, ул.Валентиновская, д.37к3 | E11: 46266
A12: 90662 | B12: Бастион | C12: Щёлково | D12: МО, г.Лосино-Петровский, площадь Революции, стр.21 | E12: 46266
A13: 50043 | B13: Визит | C13: Щёлково | D13: 141104, Московская обл, Щелковский р-н, Щелково 4 г, Беляева ул, д.41 А | E13: 46266
A14: 50804 | B14: Клининг МСК | C14: Домодедово | D14: Московская обл,Домодедово г,Центральный мкр,Каширское ш,д.91 | E14: 46266
... A435: 90028 | B435: Примекс | C435: Люберцы | D435: 140030, Московская обл, Люберецкий р-н, Малаховка п, Театральный проезд, д.16 | E435: 46280
A436: 90560 | C436: Ногинск | D436: МО, г.о.Богородский, д.Стромынь, мкр-н Ногинск-9, ул.Юбилейная, д.11А | E436: 46270
A437: 50075 | B437: Бастион | C437: Ногинск | D437: 142412, Московская обл, Ногинск , Климова ул, д.42, пом 1 | E437: 46270
A438: 90616 | B438: Бастион | C438: Ногинск | D438: МО г.Ногинск, ул.Клубная, д.3 | E438: 46270
A439: Аваренго | B439: МИКА | C439: Ногинск | D439: 142400, Московская обл, Ногинск г, Шибаевская ул, дом № 1 | E439: 46270
A440: Вопрос | B440: МИКА | C440: Ногинск | D440: 142451, Московская обл, Ногинск г, Рыбхоз п, Бисерово-парк мкр, дом № 1А | E440: 46270
A441: Додиннда | B441: МИКА | C441: Ногинск | D441: 142400, Московская обл, Ногинск г, Белякова ул, дом № 8, помещ 2 | E441: 46270
A442: Квенобани | B442: МИКА | C442: Ногинск | D442: 142412, Московская обл, Ногинск г, Климова ул, дом № 2 | E442: 46270
A443: Колывань | B443: МИКА | C443: Ногинск | D443: 142455, Москов-ская обл, Ногин-ский р-н, Элект-роугли г, Парко-вая ул, дом № 1 | E443: 46270
A444: Мутовчатая | B444: МИКА | C444: Ногинск | D444: 142436, Московская обл, Ногинск г, Боровково д, Серова ул, дом № 42, корпус А | E444: 46270
A445: Старовыжевский | B445: МИКА | C445: Ногинск | D445: 142400, Московская обл, Ногинск г, 1-ая Прудовая ул, дом № 1 | E445: 46270
A446: Хорлы | B446: МИКА | C446: Ногинск | D446: 142438, Московская обл, Ногинск г, Большое Буньково д, Ленинская ул, дом № 130 | E446: 46270
A447: Эйгер | B447: МИКА | C447: Ногинск | D447: 142402, Москов-ская обл, Но-гинск г, Чапаева ул, дом № 10, корпус А | E447: 46270
A448: 50089 | B448: Примекс | C448: Ногинск | D448: 142404, Московская обл, Ногинский р-н, Ногинск г, Советской Конституции ул, д.30 | E448: 46270
... A455: 50481 | B455: Примекс | C455: Ногинск | D455: 142450,Московская обл,Ногинский р-н,Старая Купавна г,Кирова ул,д.5 | E455: 46270
A456: 90556 | C456: Химки | D456: МО, Химки, мкр-н Подрезково, ул.Комсомольская, д.2 | E456: 46291
A457: Аптека Диетолог | B457: Альт | C457: Химки | D457: Московская обл, Химки г, Библиотечная ул, 6, пом. 001; Помещения : № 1-42 | E457: 46276
A458: Аптека Цзюлун | B458: Альт | C458: Химки | D458: Московская обл, Химки г, Юннатов ул, 10, строен. 2, пом. 003 | E458: 46276
A459: Градиско | B459: Альт | C459: Химки | D459: МО, Химки г., Елино д., д.22 | E459: 46276
A460: Дарума | B460: Альт | C460: Химки | D460: Химки г, Сходня мкр, Мичурина ул, дом № 17, корпус 5,6, кв.7 | E460: 46276
A461: Кандела | B461: Альт | C461: Химки | D461: Химки Сходня 1-йДачный переулок | E461: 46276
A462: Лалетино | B462: Альт | C462: Химки | D462: Химки г, Мельникова пр-кт, дом № 4, корпус а, кв.1 | E462: 46276
A463: Любимовский | B463: Альт | C463: Химки | D463: МО, Химки г., Германа Титова ул, д. 10А | E463: 46276
A464: Норилов | B464: Альт | C464: Химки | D464: Московская обл, Химки г, Новогорск мкр, улица Заречная, дом № строение 11/2, корпус 2 | E464: 46276
A465: Пестум | B465: Альт | C465: Химки | D465: 141407, МО, г. Химки пр-кт Юбилейный д. № 51, стр.1 | E465: 46276
A466: Риши | B466: Альт | C466: Химки | D466: Химки г, Маяковского ул, дом № 1, корпус А | E466: 46276
A467: 90210 | B467: Бастион | C467: Химки | D467: 141432, Московская область, г.о. Химки, г Химки, кв-л Клязьма, проезд Набережный, стр. 27 | E467: 46276
A468: 90482 | B468: Бастион | C468: Химки | D468: МО, Химки, мкрн.Планерная, д.23 | E468: 46276
... A1063: Штормовой | B1063: Альт | C1063: Москва Восток | D1063: 109263, Москва Чистова 16 корп 7 | E1063: 46274
A1064: РСД Дмодедово | B1064: Альфа Клининг | C1064: Домодедово | D1064: г. Домодедово мкр. Северный ул. Краснодарская 7к. 1 | E1064: 2026-08-17
A1065: 50280 | B1065: Бастион | C1065: Сергиев Посад | D1065: 141313,Московская обл,Сергиево-Посадский р-н,Сергиев Посад г,Глинки ул,д.8А | E1065: 46283
A1066: 77156 | B1066: Бастион | C1066: Москва Запад | D1066: 125252, Москва г, Новопесчаная ул, д.23, 5 | E1066: 46269
A1067: 77358 | B1067: Бастион | C1067: Москва Восток | D1067: 109052, Москва г, Нижегородская ул, д.72/2 | E1067: 46279
A1068: 77370 | B1068: Бастион | C1068: Москва Запад | D1068: 125130, Москва г, Новоподмосковный 2-й пер, д.8 | E1068: 46273
A1069: 90364 | B1069: Бастион | C1069: Сергиев Посад | D1069: 141303, Московская обл, Сергиев Посад , Красной Армии пр-кт, д.232 | E1069: 46283
A1070: 50702 | B1070: Визит | C1070: Домодедово | D1070: Домодедова, мкр Северный, ул. Гагарина, 37 | E1070: 46267
A1071: 77120 | B1071: Визит | C1071: Москва Запад | D1071: 123007, Москва г, Хорошевское ш, д.15 | E1071: 46269
A1072: 77349 | B1072: Визит | C1072: Москва Запад | D1072: 125057, Москва г, Ленинградский пркт, д.77, 2 | E1072: 46269
A1073: 244 | B1073: ДА | C1073: Наро-Фоминск | D1073: Наро-Фоминск г,Кубинское ш,д.7а/гл, | E1073: 46266
A1074: 292 | B1074: ДА | C1074: Наро-Фоминск | D1074: Наро-Фоминск г,Маршала Жукова Г.К. ул,д.52,1, | E1074: 46266
A1075: 395 | B1075: ДА | C1075: Наро-Фоминск | D1075: Наро-Фоминск г,Ленина ул,д.8, | E1075: 46266
A1076: 50731 | B1076: Клининг МСК | C1076: Ступино | D1076: Моск. обл,Ступинский р-н,Семеновское с,40 лет Победы ул,д.9А | E1076: 46275
... A1078: 50982 | B1078: Клининг МСК | C1078: Наро-Фоминск | D1078: Наро-Фоминский р-н, Селятино рп, 54, 6 | E1078: 46276
A1079: Амадео | B1079: МИКА | C1079: Рязань | D1079: 391710, Рязанская обл, Михайловский р-н, Михайлов г, Тружениц ул, дом № 26 | E1079: сент не везем
A1080: Анаксагор | B1080: МИКА | C1080: Рязань | D1080: 391170, Рязанская обл, Старожиловский р-н, Старожилово рп, Денисова ул, дом № 24, корпус а | E1080: сент не везем
A1081: Аптека Бангвеулу | B1081: МИКА | C1081: Сергиев Посад | D1081: Московская обл, Сергиево-Посадский р-н, Сергиев Посад г, Птицеградская ул, 2-б | E1081: 46283
A1082: Аяно | B1082: МИКА | C1082: Наро-Фоминск | D1082: Наро-Фоминский р-н, Селятино рп, Теннисная ул, дом № 49/1 | E1082: 46276
A1083: Баландино | B1083: МИКА | C1083: Рязань | D1083: Рязанская обл, Хирино, ул. Центральная, 2 | E1083: сент не везем
A1084: Боярский | B1084: МИКА | C1084: Рязань | D1084: 391720, Рязанская обл, Михайловский р-н, Октябрьский рп, ул. Гончарова, 7 | E1084: сент не везем
A1085: Браджо | B1085: МИКА | C1085: Домодедово | D1085: Московская обл, село Домодедово, ул. Окружная 1 | E1085: 46267
A1086: Вайфай | B1086: МИКА | C1086: Москва Восток | D1086: 109052, Москва г, Новохохловская ул, дом № 15, корпус 1 | E1086: 46276
A1087: Вэйдж | B1087: МИКА | C1087: Сергиев Посад | D1087: Московская обл, Сергиево-Посадский р-н, с.Шеметово, Садовая, д.2 В | E1087: 46283
A1088: Гвина | B1088: МИКА | C1088: Люберцы | D1088: 140054, Московская обл, Котельники г, Новая ул, дом № д.3 | E1088: 46280
A1089: Гижино | B1089: МИКА | C1089: Сергиев Посад | D1089: 141370, Московская обл, Сергиев Посад г, Хотьково г, Художественный проезд, дом № 6, корпус в | E1089: 46283
A1090: Горкино | B1090: МИКА | C1090: Рязань | D1090: г.Рязань, ул.Интернациональная, 17 А | E1090: сент не везем
A1091: Дзонаро | B1091: МИКА | C1091: Рязань | D1091: 390000, Рязанская обл, Рязань г, Кудрявцева ул, дом № 56 | E1091: сент не везем
A1092: Задорожная | B1092: МИКА | C1092: Москва Запад | D1092: 125315, Москва г, Ленинградский пр-кт, дом № 66, к. 2, помещ. 7/1 | E1092: 46273
A1093: Затушевка | B1093: МИКА | C1093: Наро-Фоминск | D1093: Наро-Фоминск г, Петровское с, дом № 71, корпус А | E1093: 46276
A1094: Исмакаево | B1094: МИКА | C1094: Москва Запад | D1094: 123182, Москва г, Волоколамское ш, дом № 24,к. 1,помещ. 7Н, 6Н, 8Н | E1094: 46273
A1095: Карнавальный | B1095: МИКА | C1095: Наро-Фоминск | D1095: Московская обл, Наро-Фоминский р-н, Калининец рп, дом № 4 | E1095: 46276
A1096: Кватроченто | B1096: МИКА | C1096: Москва Восток | D1096: 109117, Москва г, Окская ул, дом № 7, корпус 2 | E1096: 46276
A1097: Кичиро | B1097: МИКА | C1097: Рязань | D1097: 390019, Рязанская обл, Рязань г, 10 Район ул, дом № 61а | E1097: сент не везем
A1098: Кукан | B1098: МИКА | C1098: Наро-Фоминск | D1098: Наро-Фоминский район, рп.Калиненец, ул.Жилой городок-7, д. 255А | E1098: 46276
A1099: Кунгур | B1099: МИКА | C1099: Москва Запад | D1099: 123060, Москва г, Волоколамский 1-й проезд, дом № 10;д. 10,стр. 16 | E1099: 46273
A1100: Лазарев Бор | B1100: МИКА | C1100: Сергиев Посад | D1100: 141300, Московская обл, Сергиев Посад г, Вокзальная пл, дом № 1б | E1100: 46283
A1101: Лазарев бор | B1101: МИКА | C1101: Сергиев Посад | D1101: 141300, Московская обл, Сергиев Посад г, Вокзальная пл, дом № 1б | E1101: 46283
A1102: Легковерный | B1102: МИКА | C1102: Москва Юг | D1102: 117042, Москва г, Скобелевская ул, дом № 14 | E1102: 46274
A1103: Лемутье | B1103: МИКА | C1103: Сергиев Посад | D1103: 141304, Московская обл, Сергиев Посад г, Красной Армии пр-кт, дом № 3, кв.1 | E1103: 46283
A1104: Мухтарова | B1104: МИКА | C1104: Москва Восток | D1104: 109052, Москва г, Нижняя Хохловка ул, дом № 8 | E1104: 46276
A1105: Намокание | B1105: МИКА | C1105: Рязань | D1105: г.Рязань, ул.Коняева, строение 32 А | E1105: сент не везем
A1106: Новобаландино | B1106: МИКА | C1106: Рязань | D1106: Рязанский р-н, п.Листвянка, ул.Школьная, 2 Б | E1106: сент не везем
A1107: Памятка | B1107: МИКА | C1107: Сергиев Посад | D1107: 141306, Московская обл, Сергиев Посад г, Варавино д, дом № 10, корпус Б | E1107: 46283
A1108: Пачовский | B1108: МИКА | C1108: Сергиев Посад | D1108: 141303, Московская обл, Сергиев Посад г, Пограничная ул, дом № 34 | E1108: 46283
A1109: Подрессорник | B1109: МИКА | C1109: Рязань | D1109: с.Дядьково, ул.Грачи, 62, корп.1 | E1109: сент не везем
A1110: Помольщик | B1110: МИКА | C1110: Сергиев Посад | D1110: 141311, Московская обл, Сергиев Посад г, Назарьево д, дом № 56 | E1110: 46283
A1111: Поти | B1111: МИКА | C1111: Люберцы | D1111: 140054, Московская обл, Котельники г, Микрорайон Парковый ул, дом № 11 | E1111: 46280
A1112: Рухун | B1112: МИКА | C1112: Сергиев Посад | D1112: 141305, Московская обл, Сергиев Посад г, Центральная ул, дом № 1А | E1112: 46283
A1113: Саврасиха | B1113: МИКА | C1113: Сергиев Посад | D1113: 141301, Московская обл, Сергиево-Посадский р-н, Сергиев Посад г, Новоугличское ш, дом № 51 | E1113: 46283
A1114: Сокорево | B1114: МИКА | C1114: Сергиев Посад | D1114: 141303, Московская обл, Сергиев Посад г, Красной Армии пр-кт, дом № 239а/1 | E1114: 46283
A1115: Средина | B1115: МИКА | C1115: Наро-Фоминск | D1115: Наро-Фоминск г, Калининец-1 тер, дом № зд. 1 | E1115: 46276
A1116: Суналы | B1116: МИКА | C1116: Рязань | D1116: Рязанский р-н, с.Тюшево, ул.Спортивная, 4 А | E1116: сент не везем
A1117: Супермаркет | B1117: МИКА | C1117: Наро-Фоминск | D1117: Наро-Фоминский р-н, Калининец рп, дом № 4 | E1117: 46276
A1118: Таркино | B1118: МИКА | C1118: Домодедово | D1118: Московская область, Домодедово городской округ, село Ям, улица Мезенцева, д 22, пом 9Н | E1118: 46267
A1119: Текстиль | B1119: МИКА | C1119: Наро-Фоминск | D1119: Наро-Фоминский р-н, Молодежный п, дом № 33 | E1119: 46276
A1120: Телескопическая | B1120: МИКА | C1120: Москва Запад | D1120: 125319, Москва г, Кочновский проезд, дом № 4, к. 2, помещ. 24/3 | E1120: 46273
A1121: Теренций | B1121: МИКА | C1121: Рязань | D1121: 390000, Рязанская обл, Рязань г, Ленинского Комсомола ул, дом № 3, корпус а | E1121: сент не везем
...

Sheet Справочник водителей
A1: Водитель | B1: Email
A2: ВодительНФ | B2: vod2@mail.com
A3: Гончаров Артём | B3: artem@mail.ru
A4: Гришин Николай Сергеевич | B4: gri2026@mail.com
A5: Динаев Дмитрий Вадимович | B5: dost2026@mail.com
A6: Жеглов Святослав Игоревич | B6: dostavka2026@mail.com
A7: Ковылин Александр | B7: aldost@mail.com
A8: Мазим Максим Александрович | B8: vodit@mail.com
A9: Питер | B9: piter@mail.ru
A10: ФИАТ ДУКАТО | B10: fiat@mail.com
A11: Чулкин Владислав Олегович | B11: vlad@mail.com
